edupy.py
edupy-0.1.dist-info/LICENSE
edupy-0.1.dist-info/WHEEL
edupy-0.1.dist-info/METADATA
edupy-0.1.dist-info/RECORD
