Metadata-Version: 2.1
Name: edupy
Version: 0.1
Summary: An package for Education 
Home-page: https://github.com/jeremy886/edupy
License: UNKNOWN
Author: Jeremy Chen
Author-email: pypi@jeremychen.email
Classifier: License :: OSI Approved :: MIT License
